{
  "placeholder": { "stand": [26, 1] },
  "ground": {
    "grass": {
      "flat": [21, 1],
      "short": [22, 1],
      "long": [23, 1],
      "flowers": [24, 1]
     }
  },
  "things": {
    "rocks": {
      "pointyup": { "base": { "start": [1, 1], "sheet": "big_master" } },
      "pointyside": { "base": { "start": [2, 1], "sheet": "big_master" } }
    },
    "trees": {
      "oak": { "base": { "start": [1, 1], "sheet": "big_master2x3" } }
    },
    "wheats": {
      "a": {
        "1": { "base": { "start": [1, 13] } },
        "2": { "base": { "start": [2, 13] } },
        "3": { "base": { "start": [3, 13] } },
        "4": { "base": { "start": [4, 13] } }
      },
      "b": {
        "1": { "base": { "start": [1, 14] } },
        "2": { "base": { "start": [2, 14] } },
        "3": { "base": { "start": [3, 14] } },
        "4": { "base": { "start": [4, 14] } }
      },
      "c": {
        "1": { "base": { "start": [1, 15] } },
        "2": { "base": { "start": [2, 15] } },
        "3": { "base": { "start": [3, 15] } },
        "4": { "base": { "start": [4, 15] } }
      }
    },
    "--unused-- iron_ore": { "base": { "start": [1, 1] } },
    "--unused-- stump": { "base": { "start": [1, 3] } },
    "chest": { "base": { "start": [16, 1] } },
    "--unused-- sign": { "base": { "start": [19, 1] } }
  },
  "tools": {
    "pick": { "base": { "start": [11, 1], "length": 2 } },
    "axe": { "base": { "start": [11, 5], "length": 2 } },
    "scythe": { "base": { "start": [11, 7], "length": 2 } },
    "highlight": { "base": { "start": [6, 4], "length": 2 } }
  },
  "alives": {
    "dorfs": {
      "child": {
        "stand": [6, 2],
        "walk": { "start": [7, 2], "length": 2 }
      },
      "farmer":     { "stand": [3, 26], "walk": { "start": [4, 26], "length": 2 } },
      "smith":      { "stand": [3, 21], "walk": { "start": [4, 21], "length": 2 } },
      "lumberjack": { "stand": [3, 23], "walk": { "start": [4, 23], "length": 2 } },
      "baker":      { "stand": [3, 22], "walk": { "start": [4, 22], "length": 2 } },
      "miner":      { "stand": [3, 25], "walk": { "start": [4, 25], "length": 2 } },
      "builder":    { "stand": [3, 24], "walk": { "start": [4, 24], "length": 2 } },
      "--unused-- adult": {
        "--unused-- stand": [6, 1],
        "--unused-- walk": { "start": [7, 1], "length": 2, "speed": 5 }
      },
      "--unused-- old": {
        "--unused-- stand": [6, 1],
        "--unused-- walk": { "start": [7, 1], "length": 2 },
        "--unused-- addons": {
          "--unused-- beard_silver": [9, 1]
        }
      },
      "--unused-- senile": {
        "--unused-- stand": [6, 1],
        "--unused-- walk": { "start": [7, 1], "length": 2 },
        "--unused-- addons": {
          "--unused-- beard_white": [9, 2]
        }
      },
      "--unused-- ghost": {
        "--unused-- idle": { "start": [6, 3], "length": 2 },
        "--unused-- haunt": { "start": [8, 3], "length": 2 }
      }
    },
    "animals": {
      "cows": {
        "light": { "stand": [6, 5], "grazing": [6, 6] },
        "white": { "stand": [7, 5], "grazing": [7, 6] },
        "brown": { "stand": [8, 5], "grazing": [8, 6] }
      },
      "chickens": {
        "white": { "stand": [6, 7], "grazing" : [6, 8] },
        "brown": { "stand": [7, 7], "grazing" : [7, 8] },
        "black": { "stand": [8, 7], "grazing" : [8, 8] },
        "baby" : { "stand": [9, 7], "grazing" : [9, 8] }
      }
    }
  }
}
